asqi/__init__.py
asqi/config.py
asqi/container_manager.py
asqi/evaluator.py
asqi/logging_config.py
asqi/main.py
asqi/output.py
asqi/schemas.py
asqi/score_card_engine.py
asqi/validation.py
asqi/workflow.py
asqi/schemas/asqi_manifest.schema.json
asqi/schemas/asqi_score_card.schema.json
asqi/schemas/asqi_suite_config.schema.json
asqi/schemas/asqi_systems_config.schema.json
delme930-0.0.1.dev3.dist-info/METADATA
delme930-0.0.1.dev3.dist-info/WHEEL
delme930-0.0.1.dev3.dist-info/entry_points.txt
delme930-0.0.1.dev3.dist-info/licenses/LICENSE
delme930-0.0.1.dev3.dist-info/RECORD
