Metadata-Version: 2.4
Name: delme930
Version: 0.0.1.dev3
Summary: ASQI quality checks for AI systems
License-File: LICENSE
Requires-Python: >=3.12
Requires-Dist: dbos>=1.12.0
Requires-Dist: docker>=7.1.0
Requires-Dist: pydantic>=2.11.7
Requires-Dist: pyyaml>=6.0.2
Requires-Dist: rich>=14.1.0
Requires-Dist: typer>=0.16.0
